[
    {
        "input_combination": [
            {
                "type": 1,
                "code": 56,
                "origin_hash": "eb62fc478235047cf82efd8d2d989233"
            }
        ],
        "target_uinput": "keyboard",
        "output_symbol": "Control_L",
        "mapping_type": "key_macro"
    },
    {
        "input_combination": [
            {
                "type": 1,
                "code": 56,
                "origin_hash": "eb62fc478235047cf82efd8d2d989233"
            },
            {
                "type": 1,
                "code": 106,
                "origin_hash": "eb62fc478235047cf82efd8d2d989233"
            }
        ],
        "target_uinput": "keyboard",
        "output_symbol": "key_up(Control_L).key(End)",
        "mapping_type": "key_macro"
    },
    {
        "input_combination": [
            {
                "type": 1,
                "code": 56,
                "origin_hash": "eb62fc478235047cf82efd8d2d989233"
            },
            {
                "type": 1,
                "code": 105,
                "origin_hash": "eb62fc478235047cf82efd8d2d989233"
            }
        ],
        "target_uinput": "keyboard",
        "output_symbol": "key_up(Control_L).key(Home)",
        "mapping_type": "key_macro"
    },
    {
        "input_combination": [
            {
                "type": 1,
                "code": 56,
                "origin_hash": "eb62fc478235047cf82efd8d2d989233"
            },
            {
                "type": 1,
                "code": 103,
                "origin_hash": "eb62fc478235047cf82efd8d2d989233"
            }
        ],
        "target_uinput": "keyboard",
        "output_symbol": "Control_L + Home",
        "mapping_type": "key_macro"
    },
    {
        "input_combination": [
            {
                "type": 1,
                "code": 56,
                "origin_hash": "eb62fc478235047cf82efd8d2d989233"
            },
            {
                "type": 1,
                "code": 108,
                "origin_hash": "eb62fc478235047cf82efd8d2d989233"
            }
        ],
        "target_uinput": "keyboard",
        "output_symbol": "Control_L + End",
        "mapping_type": "key_macro"
    },
    {
        "input_combination": [
            {
                "type": 1,
                "code": 56,
                "origin_hash": "eb62fc478235047cf82efd8d2d989233"
            },
            {
                "type": 1,
                "code": 57,
                "origin_hash": "eb62fc478235047cf82efd8d2d989233"
            }
        ],
        "target_uinput": "keyboard",
        "output_symbol": "Super_L",
        "mapping_type": "key_macro"
    },
    {
        "input_combination": [
            {
                "type": 1,
                "code": 29,
                "origin_hash": "eb62fc478235047cf82efd8d2d989233"
            },
            {
                "type": 1,
                "code": 125,
                "origin_hash": "eb62fc478235047cf82efd8d2d989233"
            }
        ],
        "target_uinput": "keyboard",
        "output_symbol": "Super_L",
        "mapping_type": "key_macro"
    },
    {
        "input_combination": [
            {
                "type": 1,
                "code": 125,
                "origin_hash": "eb62fc478235047cf82efd8d2d989233"
            }
        ],
        "target_uinput": "keyboard",
        "output_symbol": "Control_L",
        "mapping_type": "key_macro"
    }
]
